access_modify/__init__.py
access_modify/access_modify.py
Access_Modify-1.0.8.dist-info/METADATA
Access_Modify-1.0.8.dist-info/WHEEL
Access_Modify-1.0.8.dist-info/top_level.txt
Access_Modify-1.0.8.dist-info/RECORD
