Metadata-Version: 2.1
Name: Access-Modify
Version: 1.0.8
Summary: Python module which includes private, or protected class methods for your classes.
Home-page: https://github.com/pl-Steve28-lq/
Author: Steve28
Author-email: holiday28784@gmail.com
License: UNKNOWN
Platform: UNKNOWN
Classifier: Programming Language :: Python :: 3
Classifier: License :: OSI Approved :: MIT License
Classifier: Operating System :: OS Independent
Requires-Python: >=3.6
